LICENSE
MANIFEST.in
README.md
setup.py
fabriclassed/__init__.py
fabriclassed/__init__.pyc
fabriclassed/base.py
fabriclassed/base.pyc
fabriclassed/utils.py
fabriclassed/utils.pyc
fabriclassed.egg-info/PKG-INFO
fabriclassed.egg-info/SOURCES.txt
fabriclassed.egg-info/dependency_links.txt
fabriclassed.egg-info/not-zip-safe
fabriclassed.egg-info/pbr.json
fabriclassed.egg-info/requires.txt
fabriclassed.egg-info/top_level.txt
fabriclassed/contrib/__init__.py
fabriclassed/contrib/__init__.pyc
fabriclassed/contrib/django.py
fabriclassed/contrib/django.pyc
fabriclassed/contrib/virtualenv.py
fabriclassed/contrib/virtualenv.pyc