Metadata-Version: 1.1
Name: fabriclassed
Version: 0.4.6
Summary: Class-based Fabric scripts via a Python metaprogramming hack
Home-page: https://github.com/ramusus/fabriclassed
Author: ramusus
Author-email: ramusus@gmail.com
License: BSD
Download-URL: http://pypi.python.org/pypi/fabriclassed
Platform: UNKNOWN
Classifier: Development Status :: 4 - Beta
Classifier: Environment :: Web Environment
Classifier: Intended Audience :: Developers
Classifier: License :: OSI Approved :: BSD License
Classifier: Operating System :: OS Independent
Classifier: Programming Language :: Python
Classifier: Topic :: Software Development :: Libraries :: Python Modules
